Metadata-Version: 1.0
Name: goomba
Version: 2020.1
Summary: Architecture for building creating pipelines
Home-page: https://github.com/jolespin/goomba
Author: Josh L. Espinoza
Author-email: jespinoz@jcvi.org
License: BSD-3
Platform: UNKNOWN
